pytest_docker_compose/__init__.py
pytest_docker_compose-3.2.1.dist-info/LICENSE
pytest_docker_compose-3.2.1.dist-info/METADATA
pytest_docker_compose-3.2.1.dist-info/WHEEL
pytest_docker_compose-3.2.1.dist-info/entry_points.txt
pytest_docker_compose-3.2.1.dist-info/top_level.txt
pytest_docker_compose-3.2.1.dist-info/RECORD
