Metadata-Version: 1.1
Name: pytest-docker-compose
Version: 3.2.1
Summary: Manages Docker containers during your integration tests
Home-page: https://github.com/pytest-docker-compose/pytest-docker-compose
Author: Roald Storm
Author-email: roaldstorm@gmail.com
License: UNKNOWN
Platform: UNKNOWN
Classifier: Development Status :: 5 - Production/Stable
Classifier: Framework :: Pytest
Classifier: License :: OSI Approved :: Apache Software License
Classifier: Programming Language :: Python :: 3.6
Classifier: Programming Language :: Python :: 3 :: Only
Classifier: Topic :: Software Development :: Testing
